{
	"class" : {
		"associations" : "ek 4/11/2017 14:15",
		"modelName" : "lcj 4/7/2017 10:37" },
	"instance" : {
		"features" : "lcj 4/7/2017 10:36",
		"features:" : "lcj 4/7/2017 10:36",
		"font" : "TB 4/4/2017 17:11",
		"font:" : "lcj 4/7/2017 10:37",
		"index" : "TB 4/4/2017 17:11",
		"index:" : "TB 4/4/2017 17:11",
		"pointSize" : "lcj 4/7/2017 10:37",
		"pointSize:" : "lcj 4/7/2017 10:37",
		"thread" : "lcj 4/6/2017 14:43",
		"thread:" : "lcj 4/6/2017 15:47",
		"unicodeValue" : "lcj 4/7/2017 10:36",
		"unicodeValue:" : "lcj 4/7/2017 10:36" } }
